hinocal/__init__.py
hinocal/hinocal.py
hinocal/util.py
hinocal_ecr33-1.0.0.dist-info/METADATA
hinocal_ecr33-1.0.0.dist-info/WHEEL
hinocal_ecr33-1.0.0.dist-info/entry_points.txt
hinocal_ecr33-1.0.0.dist-info/top_level.txt
hinocal_ecr33-1.0.0.dist-info/RECORD
