Metadata-Version: 2.4
Name: hinocal-ecr33
Version: 1.0.0
Summary: Google Calendar Download/Upload
Author-email: ECR33 <kenji.sakurai.hinogaku@gmail.com>
License-Expression: MIT
Project-URL: Homepage, https://github.com/ECR33/hinocal
Project-URL: Bug Tracker, https://github.com/ECR33/hinocal/issues
Classifier: Programming Language :: Python :: 3
Classifier: Operating System :: OS Independent
Requires-Python: >=3.12.3
Requires-Dist: google-api-python-client~=2.162.0
Requires-Dist: google-auth-httplib2~=0.2.0
Requires-Dist: google-auth-oauthlib~=1.2.1
Requires-Dist: icecream~=2.1.4
Requires-Dist: openpyxl~=3.1.5
Requires-Dist: python-dotenv~=1.1.0
Provides-Extra: dev
Requires-Dist: build; extra == "dev"
Requires-Dist: twine; extra == "dev"
